dtSpark/__init__.py
dtSpark/_description.txt
dtSpark/_full_name.txt
dtSpark/_licence.txt
dtSpark/_metadata.yaml
dtSpark/_name.txt
dtSpark/_version.txt
dtSpark/cli_interface.py
dtSpark/conversation_manager.py
dtSpark/launch.py
dtSpark/aws/__init__.py
dtSpark/aws/authentication.py
dtSpark/aws/bedrock.py
dtSpark/aws/costs.py
dtSpark/aws/pricing.py
dtSpark/core/__init__.py
dtSpark/core/application.py
dtSpark/core/context_compaction.py
dtSpark/daemon/__init__.py
dtSpark/daemon/__main__.py
dtSpark/daemon/action_monitor.py
dtSpark/daemon/daemon_app.py
dtSpark/daemon/daemon_manager.py
dtSpark/daemon/execution_coordinator.py
dtSpark/daemon/pid_file.py
dtSpark/database/__init__.py
dtSpark/database/autonomous_actions.py
dtSpark/database/backends.py
dtSpark/database/connection.py
dtSpark/database/conversations.py
dtSpark/database/credential_prompt.py
dtSpark/database/files.py
dtSpark/database/mcp_ops.py
dtSpark/database/messages.py
dtSpark/database/schema.py
dtSpark/database/tool_permissions.py
dtSpark/database/usage.py
dtSpark/files/__init__.py
dtSpark/files/manager.py
dtSpark/limits/__init__.py
dtSpark/limits/costs.py
dtSpark/limits/tokens.py
dtSpark/llm/__init__.py
dtSpark/llm/anthropic_direct.py
dtSpark/llm/base.py
dtSpark/llm/context_limits.py
dtSpark/llm/manager.py
dtSpark/llm/ollama.py
dtSpark/mcp_integration/__init__.py
dtSpark/mcp_integration/manager.py
dtSpark/mcp_integration/tool_selector.py
dtSpark/resources/config.yaml.template
dtSpark/safety/__init__.py
dtSpark/safety/llm_service.py
dtSpark/safety/patterns.py
dtSpark/safety/prompt_inspector.py
dtSpark/safety/violation_logger.py
dtSpark/scheduler/__init__.py
dtSpark/scheduler/creation_tools.py
dtSpark/scheduler/execution_queue.py
dtSpark/scheduler/executor.py
dtSpark/scheduler/manager.py
dtSpark/tools/__init__.py
dtSpark/tools/builtin.py
dtSpark/web/__init__.py
dtSpark/web/auth.py
dtSpark/web/dependencies.py
dtSpark/web/server.py
dtSpark/web/session.py
dtSpark/web/ssl_utils.py
dtSpark/web/web_interface.py
dtspark-1.1.0a7.dist-info/licenses/LICENSE
dtspark-1.1.0a7.dist-info/METADATA
dtspark-1.1.0a7.dist-info/WHEEL
dtspark-1.1.0a7.dist-info/entry_points.txt
dtspark-1.1.0a7.dist-info/top_level.txt
dtspark-1.1.0a7.dist-info/RECORD
