Metadata-Version: 2.4
Name: dtSpark
Version: 1.1.0a7
Summary: Secure Personal AI Research Kit - Multi-provider LLM CLI/Web interface with MCP tool integration
Home-page: https://github.com/digital-thought/dtSpark
Author: Matthew Westwood-Hill
Author-email: Matthew Westwood-Hill <matthew@digital-thought.org>
License: MIT
Project-URL: Homepage, https://github.com/digital-thought/dtSpark
Project-URL: Documentation, https://github.com/digital-thought/dtSpark#readme
Project-URL: Repository, https://github.com/digital-thought/dtSpark
Project-URL: Issues, https://github.com/digital-thought/dtSpark/issues
Keywords: llm,ai,chatbot,aws,bedrock,anthropic,claude,ollama,mcp,model-context-protocol,cli,web
Classifier: Development Status :: 4 - Beta
Classifier: Environment :: Console
Classifier: Environment :: Web Environment
Classifier: Intended Audience :: Developers
Classifier: Intended Audience :: Information Technology
Classifier: Intended Audience :: Science/Research
Classifier: License :: OSI Approved :: MIT License
Classifier: Operating System :: OS Independent
Classifier: Programming Language :: Python :: 3
Classifier: Programming Language :: Python :: 3.10
Classifier: Programming Language :: Python :: 3.11
Classifier: Programming Language :: Python :: 3.12
Classifier: Topic :: Scientific/Engineering :: Artificial Intelligence
Classifier: Topic :: Software Development :: Libraries :: Python Modules
Classifier: Topic :: Communications :: Chat
Requires-Python: >=3.10
License-File: LICENSE
Requires-Dist: boto3>=1.28.0
Requires-Dist: botocore>=1.31.0
Requires-Dist: fastapi>=0.100.0
Requires-Dist: uvicorn>=0.22.0
Requires-Dist: jinja2>=3.1.0
Requires-Dist: python-multipart>=0.0.6
Requires-Dist: sse-starlette>=1.6.0
Requires-Dist: rich>=13.0.0
Requires-Dist: prompt_toolkit>=3.0.0
Requires-Dist: httpx>=0.24.0
Requires-Dist: aiohttp>=3.8.0
Requires-Dist: mcp>=0.9.0
Requires-Dist: pyyaml>=6.0
Requires-Dist: dtPyAppFramework>=4.2.1
Requires-Dist: tiktoken>=0.5.0
Requires-Dist: ollama>=0.2.0
Requires-Dist: cryptography>=41.0.0
Requires-Dist: anthropic>=0.18.0
Requires-Dist: APScheduler>=3.10.0
Requires-Dist: markdown>=3.4.0
Requires-Dist: python-docx>=0.8.11
Requires-Dist: openpyxl>=3.1.0
Requires-Dist: python-pptx>=0.6.21
Requires-Dist: pdfplumber>=0.10.0
Requires-Dist: python-magic-bin>=0.4.14; sys_platform == "win32"
Requires-Dist: python-magic>=0.4.27; sys_platform != "win32"
Provides-Extra: dev
Requires-Dist: pytest>=7.0.0; extra == "dev"
Requires-Dist: pytest-asyncio>=0.21.0; extra == "dev"
Requires-Dist: pytest-cov>=4.0.0; extra == "dev"
Requires-Dist: black>=23.0.0; extra == "dev"
Requires-Dist: isort>=5.12.0; extra == "dev"
Requires-Dist: mypy>=1.0.0; extra == "dev"
Requires-Dist: flake8>=6.0.0; extra == "dev"
Provides-Extra: mysql
Requires-Dist: mysql-connector-python>=8.0.0; extra == "mysql"
Provides-Extra: postgresql
Requires-Dist: psycopg2-binary>=2.9.0; extra == "postgresql"
Provides-Extra: mssql
Requires-Dist: pyodbc>=4.0.0; extra == "mssql"
Provides-Extra: all-databases
Requires-Dist: mysql-connector-python>=8.0.0; extra == "all-databases"
Requires-Dist: psycopg2-binary>=2.9.0; extra == "all-databases"
Requires-Dist: pyodbc>=4.0.0; extra == "all-databases"
Dynamic: author
Dynamic: home-page
Dynamic: license-file
Dynamic: requires-python
